desco/__init__.py
desco/desco.py
desco/main.py
desco-1.4.0.dist-info/METADATA
desco-1.4.0.dist-info/WHEEL
desco-1.4.0.dist-info/entry_points.txt
desco-1.4.0.dist-info/top_level.txt
desco-1.4.0.dist-info/RECORD
