Metadata-Version: 2.4
Name: desco
Version: 1.4.0
Summary: A Python CLI tool for Dhaka Electric Supply Company Limited (DESCO) prepaid electricity accounts
Home-page: https://github.com/mdminhazulhaque/python-desco
Author: Md Minhazul Haque
Author-email: mdminhazulhaque@gmail.com
Project-URL: Bug Reports, https://github.com/mdminhazulhaque/python-desco/issues
Project-URL: Source, https://github.com/mdminhazulhaque/python-desco
Keywords: desco electricity prepaid bangladesh utility cli
Classifier: Development Status :: 4 - Beta
Classifier: Intended Audience :: End Users/Desktop
Classifier: Topic :: Utilities
Classifier: Programming Language :: Python :: 3
Classifier: Programming Language :: Python :: 3.6
Classifier: Programming Language :: Python :: 3.7
Classifier: Programming Language :: Python :: 3.8
Classifier: Programming Language :: Python :: 3.9
Classifier: Programming Language :: Python :: 3.10
Classifier: Programming Language :: Python :: 3.11
Classifier: License :: OSI Approved :: MIT License
Classifier: Operating System :: OS Independent
Requires-Python: >=3.6
Requires-Dist: requests
Requires-Dist: click
Requires-Dist: tabulate
Dynamic: author
Dynamic: author-email
Dynamic: classifier
Dynamic: description
Dynamic: description-content-type
Dynamic: home-page
Dynamic: keywords
Dynamic: project-url
Dynamic: requires-dist
Dynamic: requires-python
Dynamic: summary
